frontapp/__init__.py
frontapp/err.py
frontapp/front.py
frontapp/schemas.py
frontapp/webhook.py
frontapp-0.1.1.dist-info/WHEEL
frontapp-0.1.1.dist-info/METADATA
frontapp-0.1.1.dist-info/RECORD
