Metadata-Version: 2.1
Name: frontapp
Version: 0.1.1
Summary: 
Author: MB
Author-email: mb@m1k.pw
Requires-Python: >=3.7,<4.0
Classifier: Programming Language :: Python :: 3
Classifier: Programming Language :: Python :: 3.7
Requires-Dist: attrs (>=19.1,<20.0)
Requires-Dist: decorator (>=4.4,<5.0)
Requires-Dist: envparse (>=0.2.0,<0.3.0)
Requires-Dist: fastapi (>=0.38.1,<0.39.0)
Requires-Dist: requests (>=2.22,<3.0)
Requires-Dist: uvicorn (>=0.9.0,<0.10.0)
